Metadata-Version: 2.4
Name: marcas_bot
Version: 1.0.0
Summary: MarcasBot - A modular AI assistant system with specialized agents for sales analysis, market research, and web search capabilities. Designed to work with any brand.
Author-email: JP Alvarez <jalvare@cafesoluble.com>
License: Proprietary
Keywords: ai,assistant,sales,market-research,chatbot,langchain,multi-brand
Classifier: Development Status :: 4 - Beta
Classifier: Intended Audience :: Developers
Classifier: Intended Audience :: End Users/Desktop
Classifier: License :: Other/Proprietary License
Classifier: Operating System :: OS Independent
Classifier: Programming Language :: Python :: 3
Classifier: Programming Language :: Python :: 3.10
Classifier: Programming Language :: Python :: 3.11
Classifier: Programming Language :: Python :: 3.12
Classifier: Topic :: Scientific/Engineering :: Artificial Intelligence
Classifier: Topic :: Office/Business
Classifier: Topic :: Communications :: Chat
Requires-Python: >=3.10
Requires-Dist: fastapi==0.116.1
Requires-Dist: uvicorn==0.35.0
Requires-Dist: langchain==0.3.26
Requires-Dist: langchain-community==0.3.27
Requires-Dist: langchain-core==0.3.69
Requires-Dist: langchain-text-splitters==0.3.8
Requires-Dist: langgraph==0.5.3
Requires-Dist: langgraph-prebuilt==0.5.2
Requires-Dist: pydantic==2.11.7
Requires-Dist: python-dotenv==1.1.1
Requires-Dist: requests==2.32.4
Requires-Dist: databricks-sdk==0.59.0
Requires-Dist: databricks-ai-bridge==0.6.0
Requires-Dist: databricks-langchain==0.6.0
Requires-Dist: databricks-vectorsearch==0.57
Requires-Dist: numpy==1.26.4
Requires-Dist: pandas==2.3.1
Requires-Dist: polars==1.32.3
Requires-Dist: scikit-learn==1.7.1
Requires-Dist: gunicorn==23.0.0
Requires-Dist: python-multipart==0.0.9
Requires-Dist: langchain-openai==0.3.28
Requires-Dist: langchain-tavily==0.2.10
Requires-Dist: botbuilder-core==4.14.3
Requires-Dist: botbuilder-schema==4.14.3
Requires-Dist: botframework-connector==4.14.3
Requires-Dist: aiohttp>=3.9.0
Requires-Dist: PyJWT==2.8.0
Provides-Extra: dev
Requires-Dist: pytest>=7.0.0; extra == "dev"
Requires-Dist: pytest-cov; extra == "dev"
Requires-Dist: black; extra == "dev"
Requires-Dist: flake8; extra == "dev"
Requires-Dist: mypy; extra == "dev"
Requires-Dist: pre-commit; extra == "dev"
Requires-Dist: PyYAML; extra == "dev"
Provides-Extra: ui
Requires-Dist: streamlit; extra == "ui"
Requires-Dist: gradio; extra == "ui"
Provides-Extra: test
Requires-Dist: pytest>=7.0.0; extra == "test"
Requires-Dist: pytest-asyncio; extra == "test"
Requires-Dist: pytest-mock; extra == "test"
Requires-Dist: PyYAML; extra == "test"
